__init__.py
gears/__init__.py
gears/example.py
gears/mixins.py
gears/renderers/__init__.py
gears/renderers/exception_handlers.py
gears/renderers/mapping.py
gears/renderers/renderer.py
gears/renderers/types.py
gears/viewsets/__init__.py
gears/viewsets/permissions.py
gears/viewsets/querysets.py
gears/viewsets/serializers.py
rest_gears-0.1.1.dist-info/LICENSE
rest_gears-0.1.1.dist-info/METADATA
rest_gears-0.1.1.dist-info/WHEEL
rest_gears-0.1.1.dist-info/top_level.txt
rest_gears-0.1.1.dist-info/RECORD
