Metadata-Version: 2.1
Name: rest-gears
Version: 0.1.1
Summary: Some gears collection for getting life a little bit better.
Author-email: Alexander Yudkin <san4ezy@gmail.com>
License: MIT License        
Project-URL: Homepage, https://github.com/pypa/sampleproject
Project-URL: Bug Tracker, https://github.com/pypa/sampleproject/issues
Classifier: Programming Language :: Python :: 3
Classifier: License :: OSI Approved :: MIT License
Classifier: Operating System :: OS Independent
Requires-Python: >=3.7
License-File: LICENSE
